LICENSE
MANIFEST.in
README.md
ec2_gz.py
requirements.txt
setup.py
ec2_gazua.egg-info/PKG-INFO
ec2_gazua.egg-info/SOURCES.txt
ec2_gazua.egg-info/dependency_links.txt
ec2_gazua.egg-info/entry_points.txt
ec2_gazua.egg-info/not-zip-safe
ec2_gazua.egg-info/requires.txt
ec2_gazua.egg-info/top_level.txt
ec2gazua/__init__.py
ec2gazua/__main__.py
ec2gazua/config.py
ec2gazua/ec2.py
ec2gazua/gazua.py
ec2gazua/logger.py
ec2gazua/tmux.py
ec2gazua/utils.py
ec2gazua/widget.py