Metadata-Version: 1.2
Name: ec2-gazua
Version: 0.2.0
Summary: Easy accessing EC2 SSH through tmux
Home-page: https://github.com/leejaycoke/ec2-gazua
Author: leejaycoke
Author-email: leejaycoke@gmail.com
License: MIT License
